<?xml version="1.0" encoding="ISO-8859-1"?>

<!-- ================================================================ -->
<!--  Copyright (c) 2010-2011 Zipline Games, Inc. 					  -->
<!--  All Rights Reserved.  										  -->
<!--  http://getmoai.com											  -->
<!-- ================================================================ -->

<instructions>
	<step number="3">Connect hipbone to shoulderbone.</step>
	<step number="5">Connect collarbone to legbone.</step>
	<step number="7">Connect headbone to fingerbone.</step>
	<step number="92">Call the police.</step>
	<foo/>
	<bar/>
	<baz/>
</instructions>
